webintel/__init__.py
webintel/advanced_search_engine.py
webintel/ai_engine.py
webintel/cli.py
webintel/config.py
webintel/processor.py
webintel/utils.py
webintel-2.0.3.dist-info/licenses/LICENSE
webintel-2.0.3.dist-info/METADATA
webintel-2.0.3.dist-info/WHEEL
webintel-2.0.3.dist-info/entry_points.txt
webintel-2.0.3.dist-info/top_level.txt
webintel-2.0.3.dist-info/RECORD
